woltka/__init__.py
woltka/align.py
woltka/biom.py
woltka/classify.py
woltka/cli.py
woltka/file.py
woltka/ordinal.py
woltka/range.py
woltka/table.py
woltka/tools.py
woltka/tree.py
woltka/util.py
woltka/workflow.py
woltka/q2/README.md
woltka/q2/__init__.py
woltka/q2/_format.py
woltka/q2/_transformer.py
woltka/q2/_type.py
woltka/q2/plugin.py
woltka/q2/plugin_setup.py
woltka/q2/tests/data/align_b6o.qza
woltka/q2/tests/data/align_map.qza
woltka/q2/tests/data/align_sam.qza
woltka/q2/tests/data/alignment.sam
woltka/q2/tests/data/coords.qza
woltka/q2/tests/data/g_to_taxid.qza
woltka/q2/tests/data/gene_to_uniref.qza
woltka/q2/tests/data/metacyc_nodes.qza
woltka/q2/tests/data/nodes.qza
woltka/q2/tests/data/table.qza
woltka/q2/tests/data/taxonomy.qza
woltka/q2/tests/data/test.qza
woltka/q2/tests/data/tree.qza
woltka/tests/__init__.py
woltka/tests/test_align.py
woltka/tests/test_biom.py
woltka/tests/test_classify.py
woltka/tests/test_cli.py
woltka/tests/test_file.py
woltka/tests/test_ordinal.py
woltka/tests/test_range.py
woltka/tests/test_table.py
woltka/tests/test_tools.py
woltka/tests/test_tree.py
woltka/tests/test_util.py
woltka/tests/test_workflow.py
woltka/tests/data/README.md
woltka/tests/data/tree.nwk
woltka/tests/data/align/blastn/mux.b6o.xz
woltka/tests/data/align/bowtie2/S01.sam.xz
woltka/tests/data/align/bowtie2/S02.sam.xz
woltka/tests/data/align/bowtie2/S03.sam.xz
woltka/tests/data/align/bowtie2/S04.sam.xz
woltka/tests/data/align/bowtie2/S05.sam.xz
woltka/tests/data/align/bt2sho/S01.sam.xz
woltka/tests/data/align/bt2sho/S02.sam.xz
woltka/tests/data/align/bt2sho/S03.sam.xz
woltka/tests/data/align/bt2sho/S04.sam.xz
woltka/tests/data/align/bt2sho/S05.sam.xz
woltka/tests/data/align/burst/S01.b6.bz2
woltka/tests/data/align/burst/S02.b6.bz2
woltka/tests/data/align/burst/S03.b6.bz2
woltka/tests/data/align/burst/S04.b6.bz2
woltka/tests/data/align/burst/S05.b6.bz2
woltka/tests/data/align/burst/split/S01.map.bz2
woltka/tests/data/align/burst/split/S02.map.bz2
woltka-0.1.7.dist-info/METADATA
woltka-0.1.7.dist-info/WHEEL
woltka-0.1.7.dist-info/entry_points.txt
woltka-0.1.7.dist-info/licenses/LICENSE
woltka-0.1.7.dist-info/RECORD
