Metadata-Version: 2.3
Name: woltka
Version: 0.1.7
Summary: versatile meta-omic data classifier
Project-URL: Homepage, https://github.com/qiyunzhu/woltka
Project-URL: Documentation, https://github.com/qiyunzhu/woltka/blob/main/README.md
Project-URL: Repository, https://github.com/qiyunzhu/woltka.git
Project-URL: Issues, https://github.com/qiyunzhu/woltka/issues
Project-URL: Changelog, https://github.com/qiyunzhu/woltka/blob/main/CHANGELOG.md
Author-email: Qiyun Zhu <qiyunzhu@gmail.com>
Maintainer-email: Qiyun Zhu <qiyunzhu@gmail.com>
License: BSD 3-Clause License
License-File: LICENSE
Keywords: bioinformatics,metagenomics,microbiome
Classifier: Development Status :: 4 - Beta
Classifier: Intended Audience :: Science/Research
Classifier: License :: OSI Approved :: BSD License
Classifier: Operating System :: MacOS :: MacOS X
Classifier: Operating System :: Microsoft :: Windows
Classifier: Operating System :: OS Independent
Classifier: Operating System :: POSIX :: Linux
Classifier: Programming Language :: Python
Classifier: Programming Language :: Python :: 3
Classifier: Programming Language :: Python :: 3 :: Only
Classifier: Topic :: Scientific/Engineering
Classifier: Topic :: Scientific/Engineering :: Bio-Informatics
Requires-Python: >=3.6
Requires-Dist: biom-format
Requires-Dist: numba
